financial_metrics/__init__.py
financial_metrics/cash_flow_ratios.py
financial_metrics/efficiency_ratios.py
financial_metrics/exceptions.py
financial_metrics/leverage_ratios.py
financial_metrics/liquidity_ratios.py
financial_metrics/market_value_ratios.py
financial_metrics/profitability_ratios.py
financial_metrics-0.0.1.dist-info/LICENSE
financial_metrics-0.0.1.dist-info/METADATA
financial_metrics-0.0.1.dist-info/WHEEL
financial_metrics-0.0.1.dist-info/top_level.txt
financial_metrics-0.0.1.dist-info/RECORD
