Metadata-Version: 2.1
Name: financial-metrics
Version: 0.0.1
Summary: Financial Metrics Calculation Package
Author-email: Martin <martinthetechie@gmail.com>
Classifier: Programming Language :: Python :: 3
Classifier: License :: OSI Approved :: MIT License
Requires-Python: >=3.8
License-File: LICENSE
